api_fhir_r4/__init__.py
api_fhir_r4/admin.py
api_fhir_r4/apps.py
api_fhir_r4/defaultConfig.py
api_fhir_r4/mixins.py
api_fhir_r4/model_retrievers.py
api_fhir_r4/openapi_schema_extensions.py
api_fhir_r4/paginations.py
api_fhir_r4/permissions.py
api_fhir_r4/services.py
api_fhir_r4/signals.py
api_fhir_r4/urls.py
api_fhir_r4/validation.py
api_fhir_r4/configurations/R4ApiFhirConfig.py
api_fhir_r4/configurations/R4ClaimConfig.py
api_fhir_r4/configurations/R4CommunicationRequestConfig.py
api_fhir_r4/configurations/R4CoverageConfig.py
api_fhir_r4/configurations/R4CoverageEligibilityConfiguration.py
api_fhir_r4/configurations/R4IdentifierConfig.py
api_fhir_r4/configurations/R4InvoiceConfig.py
api_fhir_r4/configurations/R4IssueTypeConfig.py
api_fhir_r4/configurations/R4LocationConfig.py
api_fhir_r4/configurations/R4MaritalConfig.py
api_fhir_r4/configurations/R4OrganisationConfig.py
api_fhir_r4/configurations/R4PaymentNoticeConfig.py
api_fhir_r4/configurations/R4SubscriptionConfig.py
api_fhir_r4/configurations/__init__.py
api_fhir_r4/configurations/generalConfiguration.py
api_fhir_r4/configurations/moduleConfiguration.py
api_fhir_r4/containedResources/__init__.py
api_fhir_r4/containedResources/claimContainedResources.py
api_fhir_r4/containedResources/containedResourceHandler.py
api_fhir_r4/containedResources/containedResources.py
api_fhir_r4/containedResources/converterUtils.py
api_fhir_r4/containedResources/converters.py
api_fhir_r4/containedResources/serializerMixin.py
api_fhir_r4/converters/__init__.py
api_fhir_r4/converters/activityDefinitionConverter.py
api_fhir_r4/converters/claimAdminPractitionerConverter.py
api_fhir_r4/converters/claimAdminPractitionerRoleConverter.py
api_fhir_r4/converters/claimConverter.py
api_fhir_r4/converters/claimResponseConverter.py
api_fhir_r4/converters/codeSystemConverter.py
api_fhir_r4/converters/communicationConverter.py
api_fhir_r4/converters/communicationRequestConverter.py
api_fhir_r4/converters/contractConverter.py
openimis_be_api_fhir_r4-1.9.0.dist-info/licenses/LICENSE
openimis_be_api_fhir_r4-1.9.0.dist-info/licenses/LICENSE.md
openimis_be_api_fhir_r4-1.9.0.dist-info/METADATA
openimis_be_api_fhir_r4-1.9.0.dist-info/WHEEL
openimis_be_api_fhir_r4-1.9.0.dist-info/top_level.txt
openimis_be_api_fhir_r4-1.9.0.dist-info/RECORD
