Metadata-Version: 2.4
Name: openimis-be-api_fhir_r4
Version: 1.9.0
Summary: The openIMIS Backend FHIR R4 API reference module.
Home-page: https://openimis.org/
Author: Faris Ahmetasevic
Author-email: faris.ahmetasevic@hotmail.com
License: GNU AGPL v3
Classifier: Environment :: Web Environment
Classifier: Framework :: Django
Classifier: Framework :: Django :: 2.1
Classifier: Intended Audience :: Developers
Classifier: License :: OSI Approved :: GNU Affero General Public License v3
Classifier: Operating System :: OS Independent
Classifier: Programming Language :: Python
Classifier: Programming Language :: Python :: 3.5
Classifier: Programming Language :: Python :: 3.6
Classifier: Programming Language :: Python :: 3.7
License-File: LICENSE
License-File: LICENSE.md
Requires-Dist: django
Requires-Dist: django-db-signals
Requires-Dist: djangorestframework
Requires-Dist: pydantic<2
Requires-Dist: aiohttp~=3.8.5
Requires-Dist: fhir.resources>=7.0.2
Requires-Dist: asynctest==0.13.0
Requires-Dist: openimis-be-core
Requires-Dist: openimis-be-insuree
Requires-Dist: openimis-be-location
Requires-Dist: openimis-be-claim
Requires-Dist: openimis-be-policy
Requires-Dist: openimis-be-policyholder
Requires-Dist: orjson
Dynamic: author
Dynamic: author-email
Dynamic: classifier
Dynamic: description
Dynamic: description-content-type
Dynamic: home-page
Dynamic: license
Dynamic: license-file
Dynamic: requires-dist
Dynamic: summary
